dutils/__init__.py
dutils/bbox.py
dutils/constants.py
dutils/dutils.py
dutils/metrics.py
dutils/points.py
dutils/transforms.py
dutils/voxelgrid.py
dutils_pkg_sirwyver-0.6.6.5.dist-info/LICENSE
dutils_pkg_sirwyver-0.6.6.5.dist-info/METADATA
dutils_pkg_sirwyver-0.6.6.5.dist-info/WHEEL
dutils_pkg_sirwyver-0.6.6.5.dist-info/top_level.txt
dutils_pkg_sirwyver-0.6.6.5.dist-info/RECORD
