Metadata-Version: 2.1
Name: dutils-pkg-sirwyver
Version: 0.6.6.5
Summary: UUtils library for 3d stuff
Home-page: UNKNOWN
Author: Norman Müller
Author-email: norman.mueller@tum.de
License: UNKNOWN
Platform: UNKNOWN
Classifier: Programming Language :: Python :: 3
Classifier: License :: OSI Approved :: MIT License
Classifier: Operating System :: OS Independent
Requires-Python: >=3.6
